lmetric/__init__.py
lmetric/attention/__init__.py
lmetric/attention/lmetric_attention.py
lmetric/floating_ops/__init__.py
lmetric/floating_ops/lmetric_matmul.py
lmetric/llamacpp/__init__.py
lmetric/llamacpp/execute_llamacpp.py
lmetric/llamacpp/lmetric_llamacpp.py
lmetric/llamacpp/utils.py
lmetric/llm_prune/__init__.py
lmetric/llm_prune/lmetric_prune_matmul.py
lmetric/llm_quant/__init__.py
lmetric/llm_quant/custom_autotune.py
lmetric/llm_quant/gptq_quant_linear.py
lmetric/llm_quant/lmetric_quant_matmul.py
lmetric/utils/__init__.py
lmetric/utils/hf_download.py
lmetric-0.0.4.dist-info/METADATA
lmetric-0.0.4.dist-info/WHEEL
lmetric-0.0.4.dist-info/top_level.txt
lmetric-0.0.4.dist-info/RECORD
