Metadata-Version: 2.1
Name: lmetric
Version: 0.0.4
Summary: Large Model Metrics
Author: deciding
Author-email: zhangzn710@gmail.com
License: MIT
Keywords: conversion
Classifier: Development Status :: 3 - Alpha
Classifier: Intended Audience :: Developers
Classifier: License :: OSI Approved :: MIT License
Classifier: Programming Language :: Python :: 3
Requires-Dist: huggingface-hub
Requires-Dist: triton
Requires-Dist: scipy
Requires-Dist: bitsandbytes
Requires-Dist: pymeten
Requires-Dist: einops
Provides-Extra: attention
Requires-Dist: flash-attn ; extra == 'attention'
Requires-Dist: xformers ; extra == 'attention'
Provides-Extra: dev
Requires-Dist: sphinx ; extra == 'dev'
Requires-Dist: sphinx-rtd-theme ; extra == 'dev'
Requires-Dist: pytest ; extra == 'dev'
